tests
dsgnutils
