Metadata-Version: 1.0
Name: dsgnutils
Version: 0.0.9
Summary: several general purpose pythons I use all the time
Home-page: git@bitbucket.org:definex/dsgnutils.git
Author: define()
Author-email: define2.0x@gmail.com
License: Lesser GPL
Platform: UNKNOWN
